[
    {
      "searchItem": "利根川取水口"
    },
    {
      "searchItem": "木原取水場"
    },
    {
      "searchItem": "南椎尾調整池"
    },
    {
      "searchItem": "那珂川工水取水口"
    },
    {
      "searchItem": "小山取水場（利根川）"
    },
    {
      "searchItem": "霞ヶ浦浄水池"
    },
    {
      "searchItem": "１号井浄水"
    },
    {
      "searchItem": "（阿見）県南配水池"
    },
    {
      "searchItem": "緊急連絡管（阿）"
    },
    {
      "searchItem": "放流水"
    },
    {
      "searchItem": "阿見原水"
    },
    {
      "searchItem": "利根川取水"
    },
    {
      "searchItem": "水戸浄水池"
    },
    {
      "searchItem": "飯田ダム"
    },
    {
      "searchItem": "石洗堰"
    },
    {
      "searchItem": "若柴配水池（ライフライン系）"
    },
    {
      "searchItem": "土合配水池"
    },
    {
      "searchItem": "実験プラント_GAC処理水"
    },
    {
      "searchItem": "神住公民館"
    },
    {
      "searchItem": "守谷浄水場（配水）"
    },
    {
      "searchItem": "根本浄水場"
    },
    {
      "searchItem": "江戸崎浄水場"
    },
    {
      "searchItem": "つくば_臨時採水地点_01"
    },
    {
      "searchItem": "下根本5085番地25"
    },
    {
      "searchItem": "佐原組新田"
    },
    {
      "searchItem": "古渡コミュニティセンター"
    },
    {
      "searchItem": "つくば市筑波"
    },
    {
      "searchItem": "上ノ室浄水場(原水)"
    },
    {
      "searchItem": "つくば市竹園"
    },
    {
      "searchItem": "御前山ダム"
    }
  ]